cryptree/AES256cryptor.py
cryptree/__init__.py
cryptree/cryptree.py
cryptree-0.1.1.dist-info/LICENSE
cryptree-0.1.1.dist-info/METADATA
cryptree-0.1.1.dist-info/WHEEL
cryptree-0.1.1.dist-info/top_level.txt
cryptree-0.1.1.dist-info/RECORD
